{
  "updatedAt": "2026-06-08T09:18:03.426044+00:00",
  "source": "Google Sheet (manual) + Live carbonMICE",
  "event": {
    "nameEN": "Thailand Travel Mart Plus (TTM+) 2026",
    "organizer": "Tourism Authority of Thailand",
    "venue": "Nong Nooch Pattaya International Convention & Exhibition Center",
    "province": "Chonburi, Thailand",
    "dateLabel": "10 – 12 June 2026",
    "startDate": "2026-06-10",
    "endDate": "2026-06-12",
    "carbonNeutral": true,
    "standard": "ISO 14064-1:2018"
  },
  "respondents": {
    "total": 12,
    "items": [
      {
        "label": "Sellers",
        "value": 0,
        "percent": 0.0
      },
      {
        "label": "Buyers",
        "value": 0,
        "percent": 0.0
      },
      {
        "label": "Other",
        "value": 12,
        "percent": 100.0
      }
    ]
  },
  "emissions": {
    "unit": "kgCO₂eq",
    "total": 375.8,
    "scopes": [
      {
        "name": "Scope 1",
        "desc": "Direct emissions from the event",
        "value": 354.55,
        "percent": 94.3
      },
      {
        "name": "Scope 2",
        "desc": "Indirect emissions from energy",
        "value": 0.0,
        "percent": 0.0
      },
      {
        "name": "Scope 3",
        "desc": "Other indirect emissions",
        "value": 21.24,
        "percent": 5.7
      }
    ]
  },
  "offset": {
    "unit": "kgCO₂eq",
    "value": 375.8,
    "trees": 40,
    "treeNote": "medium tree, 10 years old"
  },
  "waste": {
    "unitTotal": "kg",
    "total": 0.0,
    "categories": [
      {
        "label": "Composting Food Scraps",
        "value": 0.0,
        "color": "#5FB97A",
        "percent": 0
      },
      {
        "label": "Refuse-Derived Fuel",
        "value": 0.0,
        "color": "#3E86C9",
        "percent": 0
      },
      {
        "label": "Recyclables",
        "value": 0.0,
        "color": "#E8956B",
        "percent": 0
      }
    ],
    "days": [
      "10 June",
      "11 June",
      "12 June"
    ],
    "daily": [
      {
        "label": "Composting Food Scraps",
        "color": "#5FB97A",
        "values": [
          0.0,
          0.0,
          0.0
        ]
      },
      {
        "label": "Refuse-Derived Fuel",
        "color": "#3E86C9",
        "values": [
          0.0,
          0.0,
          0.0
        ]
      },
      {
        "label": "Recyclables",
        "color": "#E8956B",
        "values": [
          0.0,
          0.0,
          0.0
        ]
      }
    ]
  },
  "wasteReduction": {
    "unit": "kgCO₂eq",
    "value": 0.0,
    "trees": 0,
    "treeNote": "medium tree, 10 years old"
  },
  "benefits": [
    {
      "icon": "🌍",
      "label": "Reduce environmental impact"
    },
    {
      "icon": "🚛",
      "label": "Reduce waste sent to disposal"
    },
    {
      "icon": "♻️",
      "label": "Increase resource value"
    },
    {
      "icon": "💡",
      "label": "Build sustainability awareness"
    }
  ]
}